{
  "experiment": "mesh_e4",
  "run": "run01",
  "desc": "Istio latency + NetworkDelay 300ms: user",
  "root_cause": "user",
  "root_cause_indices": [
    7
  ],
  "frontend_idx": 0,
  "services": [
    "front-end",
    "catalogue",
    "carts",
    "orders",
    "payment",
    "shipping",
    "user"
  ],
  "anomaly_start_second": 615,
  "baseline_seconds": 600,
  "fault_seconds": 600,
  "delay_seconds": 15,
  "rate_window": "15s",
  "chaos_apply_epoch": 1781535441,
  "dycause_dataset": "mesh_e4_mesh_run01",
  "dycause_data_dir": "D:\\project\\homework\\sockshop\\dycause_rca\\data\\mesh_e4_mesh_run01",
  "dycause_cmd": "D:\\py\\python.exe main_dycause_mp.py mesh_e4_mesh_run01 0 7 --start 615 --bef 600 --aft 600 --lag 7 --step 30 --edge_thres 0.8 --verbose 2",
  "dycause_results": [
    {
      "params": {
        "lag": 7,
        "step": 30,
        "edge_thres": 0.8
      },
      "returncode": 0,
      "log_path": "D:\\project\\homework\\sockshop\\data\\sockshop_mesh\\mesh_e4\\run01\\dycause_lag7_step30_edge0.8.log",
      "tail": [
        "          Data header                   :",
        "              1(   0 0s):front-end",
        "              2(   0 0s):catalogue",
        "              3(   0 0s):carts",
        "              4(   0 0s):orders",
        "              5(   0 0s):payment",
        "              6(   0 0s):shipping",
        "              7(   0 0s):user",
        "          Start time                    : 615",
        "          Abnormal score                : Not calculated",
        "-------------Granger interval based impact graph construction phase-------------",
        "          Calculating granger intervals:",
        "               bef len      :600",
        "               aft len      :600",
        "               lag          :7",
        "               significant  :0.1",
        "               step         :30",
        "               min len      :30",
        "               max len      :1200",
        "               segment split: [0, 30, 60, 90, 120, 150, 180, 210, 240, 270, 300, 330, 360, 390, 420, 450, 480, 510, 540, 570, 600, 630, 660, 690, 720, 750, 780, 810, 840, 870, 900, 930, 960, 990, 1020, 1050, 1080, 1110, 1140, 1170, 1200]",
        "----------------------Back trace root cause analysis phase----------------------",
        "************** Entry:  0 ***************",
        "               BFS Queue Len:     1 Output queue size:      0",
        "",
        "0.0000,[0]",
        "|    Node|       Score|",
        "  PR@1    PR@2    PR@3    PR@4    PR@5    PR@Avg     Acc",
        "------  ------  ------  ------  ------  --------  ------",
        "0.0000  0.0000  0.0000  0.0000  0.0000    0.0000  0.0000",
        "Used time: 44.1753 seconds"
      ]
    },
    {
      "params": {
        "lag": 3,
        "step": 20,
        "edge_thres": 0.4
      },
      "returncode": 0,
      "log_path": "data\\sockshop_mesh\\mesh_e4\\run01\\dycause_lag3_step20_edge0.4.log",
      "tail": [
        "          Data header                   :",
        "              1(   0 0s):front-end",
        "              2(   0 0s):catalogue",
        "              3(   0 0s):carts",
        "              4(   0 0s):orders",
        "              5(   0 0s):payment",
        "              6(   0 0s):shipping",
        "              7(   0 0s):user",
        "          Start time                    : 615",
        "          Abnormal score                : Not calculated",
        "-------------Granger interval based impact graph construction phase-------------",
        "          Calculating granger intervals:",
        "               bef len      :600",
        "               aft len      :600",
        "               lag          :3",
        "               significant  :0.1",
        "               step         :20",
        "               min len      :20",
        "               max len      :1200",
        "               segment split: [0, 20, 40, 60, 80, 100, 120, 140, 160, 180, 200, 220, 240, 260, 280, 300, 320, 340, 360, 380, 400, 420, 440, 460, 480, 500, 520, 540, 560, 580, 600, 620, 640, 660, 680, 700, 720, 740, 760, 780, 800, 820, 840, 860, 880, 900, 920, 940, 960, 980, 1000, 1020, 1040, 1060, 1080, 1100, 1120, 1140, 1160, 1180, 1200]",
        "----------------------Back trace root cause analysis phase----------------------",
        "************** Entry:  0 ***************",
        "               BFS Queue Len:     1 Output queue size:      0",
        "",
        "0.0000,[0]",
        "|    Node|       Score|",
        "  PR@1    PR@2    PR@3    PR@4    PR@5    PR@Avg     Acc",
        "------  ------  ------  ------  ------  --------  ------",
        "0.0000  0.0000  0.0000  0.0000  0.0000    0.0000  0.0000",
        "Used time: 68.3201 seconds"
      ]
    },
    {
      "params": {
        "lag": 3,
        "step": 20,
        "edge_thres": 0.6
      },
      "returncode": 0,
      "log_path": "data\\sockshop_mesh\\mesh_e4\\run01\\dycause_lag3_step20_edge0.6.log",
      "tail": [
        "0",
        "[7]",
        "################################### DyCause ####################################",
        "--------------------------------Data load phase---------------------------------",
        "          Zero fill method              : Previous then latter",
        "          Data header                   :",
        "              1(   0 0s):front-end",
        "              2(   0 0s):catalogue",
        "              3(   0 0s):carts",
        "              4(   0 0s):orders",
        "              5(   0 0s):payment",
        "              6(   0 0s):shipping",
        "              7(   0 0s):user",
        "          Start time                    : 615",
        "          Abnormal score                : Not calculated",
        "-------------Granger interval based impact graph construction phase-------------",
        "          Loading previous granger interval results: local_results_start615_bef600_aft600_lag3_sig0.1_step20_min20_max1200.pkl",
        "----------------------Back trace root cause analysis phase----------------------",
        "************** Entry:  0 ***************",
        "               BFS Queue Len:     1 Output queue size:      0",
        "",
        "0.0000,[0]",
        "|    Node|       Score|",
        "  PR@1    PR@2    PR@3    PR@4    PR@5    PR@Avg     Acc",
        "------  ------  ------  ------  ------  --------  ------",
        "0.0000  0.0000  0.0000  0.0000  0.0000    0.0000  0.0000",
        "Used time: 0.1301 seconds"
      ]
    },
    {
      "params": {
        "lag": 3,
        "step": 20,
        "edge_thres": 0.8
      },
      "returncode": 0,
      "log_path": "data\\sockshop_mesh\\mesh_e4\\run01\\dycause_lag3_step20_edge0.8.log",
      "tail": [
        "0",
        "[7]",
        "################################### DyCause ####################################",
        "--------------------------------Data load phase---------------------------------",
        "          Zero fill method              : Previous then latter",
        "          Data header                   :",
        "              1(   0 0s):front-end",
        "              2(   0 0s):catalogue",
        "              3(   0 0s):carts",
        "              4(   0 0s):orders",
        "              5(   0 0s):payment",
        "              6(   0 0s):shipping",
        "              7(   0 0s):user",
        "          Start time                    : 615",
        "          Abnormal score                : Not calculated",
        "-------------Granger interval based impact graph construction phase-------------",
        "          Loading previous granger interval results: local_results_start615_bef600_aft600_lag3_sig0.1_step20_min20_max1200.pkl",
        "----------------------Back trace root cause analysis phase----------------------",
        "************** Entry:  0 ***************",
        "               BFS Queue Len:     1 Output queue size:      0",
        "",
        "0.0000,[0]",
        "|    Node|       Score|",
        "  PR@1    PR@2    PR@3    PR@4    PR@5    PR@Avg     Acc",
        "------  ------  ------  ------  ------  --------  ------",
        "0.0000  0.0000  0.0000  0.0000  0.0000    0.0000  0.0000",
        "Used time: 0.1523 seconds"
      ]
    },
    {
      "params": {
        "lag": 3,
        "step": 30,
        "edge_thres": 0.4
      },
      "returncode": 0,
      "log_path": "data\\sockshop_mesh\\mesh_e4\\run01\\dycause_lag3_step30_edge0.4.log",
      "tail": [
        "          Data header                   :",
        "              1(   0 0s):front-end",
        "              2(   0 0s):catalogue",
        "              3(   0 0s):carts",
        "              4(   0 0s):orders",
        "              5(   0 0s):payment",
        "              6(   0 0s):shipping",
        "              7(   0 0s):user",
        "          Start time                    : 615",
        "          Abnormal score                : Not calculated",
        "-------------Granger interval based impact graph construction phase-------------",
        "          Calculating granger intervals:",
        "               bef len      :600",
        "               aft len      :600",
        "               lag          :3",
        "               significant  :0.1",
        "               step         :30",
        "               min len      :30",
        "               max len      :1200",
        "               segment split: [0, 30, 60, 90, 120, 150, 180, 210, 240, 270, 300, 330, 360, 390, 420, 450, 480, 510, 540, 570, 600, 630, 660, 690, 720, 750, 780, 810, 840, 870, 900, 930, 960, 990, 1020, 1050, 1080, 1110, 1140, 1170, 1200]",
        "----------------------Back trace root cause analysis phase----------------------",
        "************** Entry:  0 ***************",
        "               BFS Queue Len:     1 Output queue size:      0",
        "",
        "0.0000,[0]",
        "|    Node|       Score|",
        "  PR@1    PR@2    PR@3    PR@4    PR@5    PR@Avg     Acc",
        "------  ------  ------  ------  ------  --------  ------",
        "0.0000  0.0000  0.0000  0.0000  0.0000    0.0000  0.0000",
        "Used time: 35.4145 seconds"
      ]
    },
    {
      "params": {
        "lag": 3,
        "step": 30,
        "edge_thres": 0.6
      },
      "returncode": 0,
      "log_path": "data\\sockshop_mesh\\mesh_e4\\run01\\dycause_lag3_step30_edge0.6.log",
      "tail": [
        "0",
        "[7]",
        "################################### DyCause ####################################",
        "--------------------------------Data load phase---------------------------------",
        "          Zero fill method              : Previous then latter",
        "          Data header                   :",
        "              1(   0 0s):front-end",
        "              2(   0 0s):catalogue",
        "              3(   0 0s):carts",
        "              4(   0 0s):orders",
        "              5(   0 0s):payment",
        "              6(   0 0s):shipping",
        "              7(   0 0s):user",
        "          Start time                    : 615",
        "          Abnormal score                : Not calculated",
        "-------------Granger interval based impact graph construction phase-------------",
        "          Loading previous granger interval results: local_results_start615_bef600_aft600_lag3_sig0.1_step30_min30_max1200.pkl",
        "----------------------Back trace root cause analysis phase----------------------",
        "************** Entry:  0 ***************",
        "               BFS Queue Len:     1 Output queue size:      0",
        "",
        "0.0000,[0]",
        "|    Node|       Score|",
        "  PR@1    PR@2    PR@3    PR@4    PR@5    PR@Avg     Acc",
        "------  ------  ------  ------  ------  --------  ------",
        "0.0000  0.0000  0.0000  0.0000  0.0000    0.0000  0.0000",
        "Used time: 0.1682 seconds"
      ]
    },
    {
      "params": {
        "lag": 3,
        "step": 30,
        "edge_thres": 0.8
      },
      "returncode": 0,
      "log_path": "data\\sockshop_mesh\\mesh_e4\\run01\\dycause_lag3_step30_edge0.8.log",
      "tail": [
        "0",
        "[7]",
        "################################### DyCause ####################################",
        "--------------------------------Data load phase---------------------------------",
        "          Zero fill method              : Previous then latter",
        "          Data header                   :",
        "              1(   0 0s):front-end",
        "              2(   0 0s):catalogue",
        "              3(   0 0s):carts",
        "              4(   0 0s):orders",
        "              5(   0 0s):payment",
        "              6(   0 0s):shipping",
        "              7(   0 0s):user",
        "          Start time                    : 615",
        "          Abnormal score                : Not calculated",
        "-------------Granger interval based impact graph construction phase-------------",
        "          Loading previous granger interval results: local_results_start615_bef600_aft600_lag3_sig0.1_step30_min30_max1200.pkl",
        "----------------------Back trace root cause analysis phase----------------------",
        "************** Entry:  0 ***************",
        "               BFS Queue Len:     1 Output queue size:      0",
        "",
        "0.0000,[0]",
        "|    Node|       Score|",
        "  PR@1    PR@2    PR@3    PR@4    PR@5    PR@Avg     Acc",
        "------  ------  ------  ------  ------  --------  ------",
        "0.0000  0.0000  0.0000  0.0000  0.0000    0.0000  0.0000",
        "Used time: 0.1516 seconds"
      ]
    },
    {
      "params": {
        "lag": 3,
        "step": 60,
        "edge_thres": 0.4
      },
      "returncode": 0,
      "log_path": "data\\sockshop_mesh\\mesh_e4\\run01\\dycause_lag3_step60_edge0.4.log",
      "tail": [
        "          Data header                   :",
        "              1(   0 0s):front-end",
        "              2(   0 0s):catalogue",
        "              3(   0 0s):carts",
        "              4(   0 0s):orders",
        "              5(   0 0s):payment",
        "              6(   0 0s):shipping",
        "              7(   0 0s):user",
        "          Start time                    : 615",
        "          Abnormal score                : Not calculated",
        "-------------Granger interval based impact graph construction phase-------------",
        "          Calculating granger intervals:",
        "               bef len      :600",
        "               aft len      :600",
        "               lag          :3",
        "               significant  :0.1",
        "               step         :60",
        "               min len      :60",
        "               max len      :1200",
        "               segment split: [0, 60, 120, 180, 240, 300, 360, 420, 480, 540, 600, 660, 720, 780, 840, 900, 960, 1020, 1080, 1140, 1200]",
        "----------------------Back trace root cause analysis phase----------------------",
        "************** Entry:  0 ***************",
        "               BFS Queue Len:     1 Output queue size:      0",
        "",
        "0.0000,[0]",
        "|    Node|       Score|",
        "  PR@1    PR@2    PR@3    PR@4    PR@5    PR@Avg     Acc",
        "------  ------  ------  ------  ------  --------  ------",
        "0.0000  0.0000  0.0000  0.0000  0.0000    0.0000  0.0000",
        "Used time: 14.2131 seconds"
      ]
    },
    {
      "params": {
        "lag": 3,
        "step": 60,
        "edge_thres": 0.6
      },
      "returncode": 0,
      "log_path": "data\\sockshop_mesh\\mesh_e4\\run01\\dycause_lag3_step60_edge0.6.log",
      "tail": [
        "0",
        "[7]",
        "################################### DyCause ####################################",
        "--------------------------------Data load phase---------------------------------",
        "          Zero fill method              : Previous then latter",
        "          Data header                   :",
        "              1(   0 0s):front-end",
        "              2(   0 0s):catalogue",
        "              3(   0 0s):carts",
        "              4(   0 0s):orders",
        "              5(   0 0s):payment",
        "              6(   0 0s):shipping",
        "              7(   0 0s):user",
        "          Start time                    : 615",
        "          Abnormal score                : Not calculated",
        "-------------Granger interval based impact graph construction phase-------------",
        "          Loading previous granger interval results: local_results_start615_bef600_aft600_lag3_sig0.1_step60_min60_max1200.pkl",
        "----------------------Back trace root cause analysis phase----------------------",
        "************** Entry:  0 ***************",
        "               BFS Queue Len:     1 Output queue size:      0",
        "",
        "0.0000,[0]",
        "|    Node|       Score|",
        "  PR@1    PR@2    PR@3    PR@4    PR@5    PR@Avg     Acc",
        "------  ------  ------  ------  ------  --------  ------",
        "0.0000  0.0000  0.0000  0.0000  0.0000    0.0000  0.0000",
        "Used time: 0.1271 seconds"
      ]
    },
    {
      "params": {
        "lag": 3,
        "step": 60,
        "edge_thres": 0.8
      },
      "returncode": 0,
      "log_path": "data\\sockshop_mesh\\mesh_e4\\run01\\dycause_lag3_step60_edge0.8.log",
      "tail": [
        "0",
        "[7]",
        "################################### DyCause ####################################",
        "--------------------------------Data load phase---------------------------------",
        "          Zero fill method              : Previous then latter",
        "          Data header                   :",
        "              1(   0 0s):front-end",
        "              2(   0 0s):catalogue",
        "              3(   0 0s):carts",
        "              4(   0 0s):orders",
        "              5(   0 0s):payment",
        "              6(   0 0s):shipping",
        "              7(   0 0s):user",
        "          Start time                    : 615",
        "          Abnormal score                : Not calculated",
        "-------------Granger interval based impact graph construction phase-------------",
        "          Loading previous granger interval results: local_results_start615_bef600_aft600_lag3_sig0.1_step60_min60_max1200.pkl",
        "----------------------Back trace root cause analysis phase----------------------",
        "************** Entry:  0 ***************",
        "               BFS Queue Len:     1 Output queue size:      0",
        "",
        "0.0000,[0]",
        "|    Node|       Score|",
        "  PR@1    PR@2    PR@3    PR@4    PR@5    PR@Avg     Acc",
        "------  ------  ------  ------  ------  --------  ------",
        "0.0000  0.0000  0.0000  0.0000  0.0000    0.0000  0.0000",
        "Used time: 0.1057 seconds"
      ]
    },
    {
      "params": {
        "lag": 5,
        "step": 20,
        "edge_thres": 0.4
      },
      "returncode": 0,
      "log_path": "data\\sockshop_mesh\\mesh_e4\\run01\\dycause_lag5_step20_edge0.4.log",
      "tail": [
        "          Data header                   :",
        "              1(   0 0s):front-end",
        "              2(   0 0s):catalogue",
        "              3(   0 0s):carts",
        "              4(   0 0s):orders",
        "              5(   0 0s):payment",
        "              6(   0 0s):shipping",
        "              7(   0 0s):user",
        "          Start time                    : 615",
        "          Abnormal score                : Not calculated",
        "-------------Granger interval based impact graph construction phase-------------",
        "          Calculating granger intervals:",
        "               bef len      :600",
        "               aft len      :600",
        "               lag          :5",
        "               significant  :0.1",
        "               step         :20",
        "               min len      :20",
        "               max len      :1200",
        "               segment split: [0, 20, 40, 60, 80, 100, 120, 140, 160, 180, 200, 220, 240, 260, 280, 300, 320, 340, 360, 380, 400, 420, 440, 460, 480, 500, 520, 540, 560, 580, 600, 620, 640, 660, 680, 700, 720, 740, 760, 780, 800, 820, 840, 860, 880, 900, 920, 940, 960, 980, 1000, 1020, 1040, 1060, 1080, 1100, 1120, 1140, 1160, 1180, 1200]",
        "----------------------Back trace root cause analysis phase----------------------",
        "************** Entry:  0 ***************",
        "               BFS Queue Len:     1 Output queue size:      0",
        "",
        "0.0000,[0]",
        "|    Node|       Score|",
        "  PR@1    PR@2    PR@3    PR@4    PR@5    PR@Avg     Acc",
        "------  ------  ------  ------  ------  --------  ------",
        "0.0000  0.0000  0.0000  0.0000  0.0000    0.0000  0.0000",
        "Used time: 75.0214 seconds"
      ]
    },
    {
      "params": {
        "lag": 5,
        "step": 20,
        "edge_thres": 0.6
      },
      "returncode": 0,
      "log_path": "data\\sockshop_mesh\\mesh_e4\\run01\\dycause_lag5_step20_edge0.6.log",
      "tail": [
        "0",
        "[7]",
        "################################### DyCause ####################################",
        "--------------------------------Data load phase---------------------------------",
        "          Zero fill method              : Previous then latter",
        "          Data header                   :",
        "              1(   0 0s):front-end",
        "              2(   0 0s):catalogue",
        "              3(   0 0s):carts",
        "              4(   0 0s):orders",
        "              5(   0 0s):payment",
        "              6(   0 0s):shipping",
        "              7(   0 0s):user",
        "          Start time                    : 615",
        "          Abnormal score                : Not calculated",
        "-------------Granger interval based impact graph construction phase-------------",
        "          Loading previous granger interval results: local_results_start615_bef600_aft600_lag5_sig0.1_step20_min20_max1200.pkl",
        "----------------------Back trace root cause analysis phase----------------------",
        "************** Entry:  0 ***************",
        "               BFS Queue Len:     1 Output queue size:      0",
        "",
        "0.0000,[0]",
        "|    Node|       Score|",
        "  PR@1    PR@2    PR@3    PR@4    PR@5    PR@Avg     Acc",
        "------  ------  ------  ------  ------  --------  ------",
        "0.0000  0.0000  0.0000  0.0000  0.0000    0.0000  0.0000",
        "Used time: 0.1342 seconds"
      ]
    },
    {
      "params": {
        "lag": 5,
        "step": 20,
        "edge_thres": 0.8
      },
      "returncode": 0,
      "log_path": "data\\sockshop_mesh\\mesh_e4\\run01\\dycause_lag5_step20_edge0.8.log",
      "tail": [
        "0",
        "[7]",
        "################################### DyCause ####################################",
        "--------------------------------Data load phase---------------------------------",
        "          Zero fill method              : Previous then latter",
        "          Data header                   :",
        "              1(   0 0s):front-end",
        "              2(   0 0s):catalogue",
        "              3(   0 0s):carts",
        "              4(   0 0s):orders",
        "              5(   0 0s):payment",
        "              6(   0 0s):shipping",
        "              7(   0 0s):user",
        "          Start time                    : 615",
        "          Abnormal score                : Not calculated",
        "-------------Granger interval based impact graph construction phase-------------",
        "          Loading previous granger interval results: local_results_start615_bef600_aft600_lag5_sig0.1_step20_min20_max1200.pkl",
        "----------------------Back trace root cause analysis phase----------------------",
        "************** Entry:  0 ***************",
        "               BFS Queue Len:     1 Output queue size:      0",
        "",
        "0.0000,[0]",
        "|    Node|       Score|",
        "  PR@1    PR@2    PR@3    PR@4    PR@5    PR@Avg     Acc",
        "------  ------  ------  ------  ------  --------  ------",
        "0.0000  0.0000  0.0000  0.0000  0.0000    0.0000  0.0000",
        "Used time: 0.1424 seconds"
      ]
    },
    {
      "params": {
        "lag": 5,
        "step": 30,
        "edge_thres": 0.4
      },
      "returncode": 0,
      "log_path": "data\\sockshop_mesh\\mesh_e4\\run01\\dycause_lag5_step30_edge0.4.log",
      "tail": [
        "          Data header                   :",
        "              1(   0 0s):front-end",
        "              2(   0 0s):catalogue",
        "              3(   0 0s):carts",
        "              4(   0 0s):orders",
        "              5(   0 0s):payment",
        "              6(   0 0s):shipping",
        "              7(   0 0s):user",
        "          Start time                    : 615",
        "          Abnormal score                : Not calculated",
        "-------------Granger interval based impact graph construction phase-------------",
        "          Calculating granger intervals:",
        "               bef len      :600",
        "               aft len      :600",
        "               lag          :5",
        "               significant  :0.1",
        "               step         :30",
        "               min len      :30",
        "               max len      :1200",
        "               segment split: [0, 30, 60, 90, 120, 150, 180, 210, 240, 270, 300, 330, 360, 390, 420, 450, 480, 510, 540, 570, 600, 630, 660, 690, 720, 750, 780, 810, 840, 870, 900, 930, 960, 990, 1020, 1050, 1080, 1110, 1140, 1170, 1200]",
        "----------------------Back trace root cause analysis phase----------------------",
        "************** Entry:  0 ***************",
        "               BFS Queue Len:     1 Output queue size:      0",
        "",
        "0.0000,[0]",
        "|    Node|       Score|",
        "  PR@1    PR@2    PR@3    PR@4    PR@5    PR@Avg     Acc",
        "------  ------  ------  ------  ------  --------  ------",
        "0.0000  0.0000  0.0000  0.0000  0.0000    0.0000  0.0000",
        "Used time: 40.8035 seconds"
      ]
    },
    {
      "params": {
        "lag": 5,
        "step": 30,
        "edge_thres": 0.6
      },
      "returncode": 0,
      "log_path": "data\\sockshop_mesh\\mesh_e4\\run01\\dycause_lag5_step30_edge0.6.log",
      "tail": [
        "0",
        "[7]",
        "################################### DyCause ####################################",
        "--------------------------------Data load phase---------------------------------",
        "          Zero fill method              : Previous then latter",
        "          Data header                   :",
        "              1(   0 0s):front-end",
        "              2(   0 0s):catalogue",
        "              3(   0 0s):carts",
        "              4(   0 0s):orders",
        "              5(   0 0s):payment",
        "              6(   0 0s):shipping",
        "              7(   0 0s):user",
        "          Start time                    : 615",
        "          Abnormal score                : Not calculated",
        "-------------Granger interval based impact graph construction phase-------------",
        "          Loading previous granger interval results: local_results_start615_bef600_aft600_lag5_sig0.1_step30_min30_max1200.pkl",
        "----------------------Back trace root cause analysis phase----------------------",
        "************** Entry:  0 ***************",
        "               BFS Queue Len:     1 Output queue size:      0",
        "",
        "0.0000,[0]",
        "|    Node|       Score|",
        "  PR@1    PR@2    PR@3    PR@4    PR@5    PR@Avg     Acc",
        "------  ------  ------  ------  ------  --------  ------",
        "0.0000  0.0000  0.0000  0.0000  0.0000    0.0000  0.0000",
        "Used time: 0.1361 seconds"
      ]
    },
    {
      "params": {
        "lag": 5,
        "step": 30,
        "edge_thres": 0.8
      },
      "returncode": 0,
      "log_path": "data\\sockshop_mesh\\mesh_e4\\run01\\dycause_lag5_step30_edge0.8.log",
      "tail": [
        "0",
        "[7]",
        "################################### DyCause ####################################",
        "--------------------------------Data load phase---------------------------------",
        "          Zero fill method              : Previous then latter",
        "          Data header                   :",
        "              1(   0 0s):front-end",
        "              2(   0 0s):catalogue",
        "              3(   0 0s):carts",
        "              4(   0 0s):orders",
        "              5(   0 0s):payment",
        "              6(   0 0s):shipping",
        "              7(   0 0s):user",
        "          Start time                    : 615",
        "          Abnormal score                : Not calculated",
        "-------------Granger interval based impact graph construction phase-------------",
        "          Loading previous granger interval results: local_results_start615_bef600_aft600_lag5_sig0.1_step30_min30_max1200.pkl",
        "----------------------Back trace root cause analysis phase----------------------",
        "************** Entry:  0 ***************",
        "               BFS Queue Len:     1 Output queue size:      0",
        "",
        "0.0000,[0]",
        "|    Node|       Score|",
        "  PR@1    PR@2    PR@3    PR@4    PR@5    PR@Avg     Acc",
        "------  ------  ------  ------  ------  --------  ------",
        "0.0000  0.0000  0.0000  0.0000  0.0000    0.0000  0.0000",
        "Used time: 0.1212 seconds"
      ]
    },
    {
      "params": {
        "lag": 5,
        "step": 60,
        "edge_thres": 0.4
      },
      "returncode": 0,
      "log_path": "data\\sockshop_mesh\\mesh_e4\\run01\\dycause_lag5_step60_edge0.4.log",
      "tail": [
        "          Data header                   :",
        "              1(   0 0s):front-end",
        "              2(   0 0s):catalogue",
        "              3(   0 0s):carts",
        "              4(   0 0s):orders",
        "              5(   0 0s):payment",
        "              6(   0 0s):shipping",
        "              7(   0 0s):user",
        "          Start time                    : 615",
        "          Abnormal score                : Not calculated",
        "-------------Granger interval based impact graph construction phase-------------",
        "          Calculating granger intervals:",
        "               bef len      :600",
        "               aft len      :600",
        "               lag          :5",
        "               significant  :0.1",
        "               step         :60",
        "               min len      :60",
        "               max len      :1200",
        "               segment split: [0, 60, 120, 180, 240, 300, 360, 420, 480, 540, 600, 660, 720, 780, 840, 900, 960, 1020, 1080, 1140, 1200]",
        "----------------------Back trace root cause analysis phase----------------------",
        "************** Entry:  0 ***************",
        "               BFS Queue Len:     1 Output queue size:      0",
        "",
        "0.0000,[0]",
        "|    Node|       Score|",
        "  PR@1    PR@2    PR@3    PR@4    PR@5    PR@Avg     Acc",
        "------  ------  ------  ------  ------  --------  ------",
        "0.0000  0.0000  0.0000  0.0000  0.0000    0.0000  0.0000",
        "Used time: 15.6766 seconds"
      ]
    },
    {
      "params": {
        "lag": 5,
        "step": 60,
        "edge_thres": 0.6
      },
      "returncode": 0,
      "log_path": "data\\sockshop_mesh\\mesh_e4\\run01\\dycause_lag5_step60_edge0.6.log",
      "tail": [
        "0",
        "[7]",
        "################################### DyCause ####################################",
        "--------------------------------Data load phase---------------------------------",
        "          Zero fill method              : Previous then latter",
        "          Data header                   :",
        "              1(   0 0s):front-end",
        "              2(   0 0s):catalogue",
        "              3(   0 0s):carts",
        "              4(   0 0s):orders",
        "              5(   0 0s):payment",
        "              6(   0 0s):shipping",
        "              7(   0 0s):user",
        "          Start time                    : 615",
        "          Abnormal score                : Not calculated",
        "-------------Granger interval based impact graph construction phase-------------",
        "          Loading previous granger interval results: local_results_start615_bef600_aft600_lag5_sig0.1_step60_min60_max1200.pkl",
        "----------------------Back trace root cause analysis phase----------------------",
        "************** Entry:  0 ***************",
        "               BFS Queue Len:     1 Output queue size:      0",
        "",
        "0.0000,[0]",
        "|    Node|       Score|",
        "  PR@1    PR@2    PR@3    PR@4    PR@5    PR@Avg     Acc",
        "------  ------  ------  ------  ------  --------  ------",
        "0.0000  0.0000  0.0000  0.0000  0.0000    0.0000  0.0000",
        "Used time: 0.1020 seconds"
      ]
    },
    {
      "params": {
        "lag": 5,
        "step": 60,
        "edge_thres": 0.8
      },
      "returncode": 0,
      "log_path": "data\\sockshop_mesh\\mesh_e4\\run01\\dycause_lag5_step60_edge0.8.log",
      "tail": [
        "0",
        "[7]",
        "################################### DyCause ####################################",
        "--------------------------------Data load phase---------------------------------",
        "          Zero fill method              : Previous then latter",
        "          Data header                   :",
        "              1(   0 0s):front-end",
        "              2(   0 0s):catalogue",
        "              3(   0 0s):carts",
        "              4(   0 0s):orders",
        "              5(   0 0s):payment",
        "              6(   0 0s):shipping",
        "              7(   0 0s):user",
        "          Start time                    : 615",
        "          Abnormal score                : Not calculated",
        "-------------Granger interval based impact graph construction phase-------------",
        "          Loading previous granger interval results: local_results_start615_bef600_aft600_lag5_sig0.1_step60_min60_max1200.pkl",
        "----------------------Back trace root cause analysis phase----------------------",
        "************** Entry:  0 ***************",
        "               BFS Queue Len:     1 Output queue size:      0",
        "",
        "0.0000,[0]",
        "|    Node|       Score|",
        "  PR@1    PR@2    PR@3    PR@4    PR@5    PR@Avg     Acc",
        "------  ------  ------  ------  ------  --------  ------",
        "0.0000  0.0000  0.0000  0.0000  0.0000    0.0000  0.0000",
        "Used time: 0.1121 seconds"
      ]
    },
    {
      "params": {
        "lag": 7,
        "step": 30,
        "edge_thres": 0.4
      },
      "returncode": 0,
      "log_path": "data\\sockshop_mesh\\mesh_e4\\run01\\dycause_lag7_step30_edge0.4.log",
      "tail": [
        "0",
        "[7]",
        "################################### DyCause ####################################",
        "--------------------------------Data load phase---------------------------------",
        "          Zero fill method              : Previous then latter",
        "          Data header                   :",
        "              1(   0 0s):front-end",
        "              2(   0 0s):catalogue",
        "              3(   0 0s):carts",
        "              4(   0 0s):orders",
        "              5(   0 0s):payment",
        "              6(   0 0s):shipping",
        "              7(   0 0s):user",
        "          Start time                    : 615",
        "          Abnormal score                : Not calculated",
        "-------------Granger interval based impact graph construction phase-------------",
        "          Loading previous granger interval results: local_results_start615_bef600_aft600_lag7_sig0.1_step30_min30_max1200.pkl",
        "----------------------Back trace root cause analysis phase----------------------",
        "************** Entry:  0 ***************",
        "               BFS Queue Len:     1 Output queue size:      0",
        "",
        "0.0000,[0]",
        "|    Node|       Score|",
        "  PR@1    PR@2    PR@3    PR@4    PR@5    PR@Avg     Acc",
        "------  ------  ------  ------  ------  --------  ------",
        "0.0000  0.0000  0.0000  0.0000  0.0000    0.0000  0.0000",
        "Used time: 0.1328 seconds"
      ]
    },
    {
      "params": {
        "lag": 7,
        "step": 30,
        "edge_thres": 0.6
      },
      "returncode": 0,
      "log_path": "data\\sockshop_mesh\\mesh_e4\\run01\\dycause_lag7_step30_edge0.6.log",
      "tail": [
        "0",
        "[7]",
        "################################### DyCause ####################################",
        "--------------------------------Data load phase---------------------------------",
        "          Zero fill method              : Previous then latter",
        "          Data header                   :",
        "              1(   0 0s):front-end",
        "              2(   0 0s):catalogue",
        "              3(   0 0s):carts",
        "              4(   0 0s):orders",
        "              5(   0 0s):payment",
        "              6(   0 0s):shipping",
        "              7(   0 0s):user",
        "          Start time                    : 615",
        "          Abnormal score                : Not calculated",
        "-------------Granger interval based impact graph construction phase-------------",
        "          Loading previous granger interval results: local_results_start615_bef600_aft600_lag7_sig0.1_step30_min30_max1200.pkl",
        "----------------------Back trace root cause analysis phase----------------------",
        "************** Entry:  0 ***************",
        "               BFS Queue Len:     1 Output queue size:      0",
        "",
        "0.0000,[0]",
        "|    Node|       Score|",
        "  PR@1    PR@2    PR@3    PR@4    PR@5    PR@Avg     Acc",
        "------  ------  ------  ------  ------  --------  ------",
        "0.0000  0.0000  0.0000  0.0000  0.0000    0.0000  0.0000",
        "Used time: 0.1130 seconds"
      ]
    },
    {
      "params": {
        "lag": 7,
        "step": 30,
        "edge_thres": 0.8
      },
      "returncode": 0,
      "log_path": "data\\sockshop_mesh\\mesh_e4\\run01\\dycause_lag7_step30_edge0.8.log",
      "tail": [
        "0",
        "[7]",
        "################################### DyCause ####################################",
        "--------------------------------Data load phase---------------------------------",
        "          Zero fill method              : Previous then latter",
        "          Data header                   :",
        "              1(   0 0s):front-end",
        "              2(   0 0s):catalogue",
        "              3(   0 0s):carts",
        "              4(   0 0s):orders",
        "              5(   0 0s):payment",
        "              6(   0 0s):shipping",
        "              7(   0 0s):user",
        "          Start time                    : 615",
        "          Abnormal score                : Not calculated",
        "-------------Granger interval based impact graph construction phase-------------",
        "          Loading previous granger interval results: local_results_start615_bef600_aft600_lag7_sig0.1_step30_min30_max1200.pkl",
        "----------------------Back trace root cause analysis phase----------------------",
        "************** Entry:  0 ***************",
        "               BFS Queue Len:     1 Output queue size:      0",
        "",
        "0.0000,[0]",
        "|    Node|       Score|",
        "  PR@1    PR@2    PR@3    PR@4    PR@5    PR@Avg     Acc",
        "------  ------  ------  ------  ------  --------  ------",
        "0.0000  0.0000  0.0000  0.0000  0.0000    0.0000  0.0000",
        "Used time: 0.1182 seconds"
      ]
    },
    {
      "params": {
        "lag": 7,
        "step": 60,
        "edge_thres": 0.4
      },
      "returncode": 0,
      "log_path": "data\\sockshop_mesh\\mesh_e4\\run01\\dycause_lag7_step60_edge0.4.log",
      "tail": [
        "          Data header                   :",
        "              1(   0 0s):front-end",
        "              2(   0 0s):catalogue",
        "              3(   0 0s):carts",
        "              4(   0 0s):orders",
        "              5(   0 0s):payment",
        "              6(   0 0s):shipping",
        "              7(   0 0s):user",
        "          Start time                    : 615",
        "          Abnormal score                : Not calculated",
        "-------------Granger interval based impact graph construction phase-------------",
        "          Calculating granger intervals:",
        "               bef len      :600",
        "               aft len      :600",
        "               lag          :7",
        "               significant  :0.1",
        "               step         :60",
        "               min len      :60",
        "               max len      :1200",
        "               segment split: [0, 60, 120, 180, 240, 300, 360, 420, 480, 540, 600, 660, 720, 780, 840, 900, 960, 1020, 1080, 1140, 1200]",
        "----------------------Back trace root cause analysis phase----------------------",
        "************** Entry:  0 ***************",
        "               BFS Queue Len:     1 Output queue size:      0",
        "",
        "0.0000,[0]",
        "|    Node|       Score|",
        "  PR@1    PR@2    PR@3    PR@4    PR@5    PR@Avg     Acc",
        "------  ------  ------  ------  ------  --------  ------",
        "0.0000  0.0000  0.0000  0.0000  0.0000    0.0000  0.0000",
        "Used time: 17.4553 seconds"
      ]
    },
    {
      "params": {
        "lag": 7,
        "step": 60,
        "edge_thres": 0.6
      },
      "returncode": 0,
      "log_path": "data\\sockshop_mesh\\mesh_e4\\run01\\dycause_lag7_step60_edge0.6.log",
      "tail": [
        "0",
        "[7]",
        "################################### DyCause ####################################",
        "--------------------------------Data load phase---------------------------------",
        "          Zero fill method              : Previous then latter",
        "          Data header                   :",
        "              1(   0 0s):front-end",
        "              2(   0 0s):catalogue",
        "              3(   0 0s):carts",
        "              4(   0 0s):orders",
        "              5(   0 0s):payment",
        "              6(   0 0s):shipping",
        "              7(   0 0s):user",
        "          Start time                    : 615",
        "          Abnormal score                : Not calculated",
        "-------------Granger interval based impact graph construction phase-------------",
        "          Loading previous granger interval results: local_results_start615_bef600_aft600_lag7_sig0.1_step60_min60_max1200.pkl",
        "----------------------Back trace root cause analysis phase----------------------",
        "************** Entry:  0 ***************",
        "               BFS Queue Len:     1 Output queue size:      0",
        "",
        "0.0000,[0]",
        "|    Node|       Score|",
        "  PR@1    PR@2    PR@3    PR@4    PR@5    PR@Avg     Acc",
        "------  ------  ------  ------  ------  --------  ------",
        "0.0000  0.0000  0.0000  0.0000  0.0000    0.0000  0.0000",
        "Used time: 0.1342 seconds"
      ]
    },
    {
      "params": {
        "lag": 7,
        "step": 60,
        "edge_thres": 0.8
      },
      "returncode": 0,
      "log_path": "data\\sockshop_mesh\\mesh_e4\\run01\\dycause_lag7_step60_edge0.8.log",
      "tail": [
        "0",
        "[7]",
        "################################### DyCause ####################################",
        "--------------------------------Data load phase---------------------------------",
        "          Zero fill method              : Previous then latter",
        "          Data header                   :",
        "              1(   0 0s):front-end",
        "              2(   0 0s):catalogue",
        "              3(   0 0s):carts",
        "              4(   0 0s):orders",
        "              5(   0 0s):payment",
        "              6(   0 0s):shipping",
        "              7(   0 0s):user",
        "          Start time                    : 615",
        "          Abnormal score                : Not calculated",
        "-------------Granger interval based impact graph construction phase-------------",
        "          Loading previous granger interval results: local_results_start615_bef600_aft600_lag7_sig0.1_step60_min60_max1200.pkl",
        "----------------------Back trace root cause analysis phase----------------------",
        "************** Entry:  0 ***************",
        "               BFS Queue Len:     1 Output queue size:      0",
        "",
        "0.0000,[0]",
        "|    Node|       Score|",
        "  PR@1    PR@2    PR@3    PR@4    PR@5    PR@Avg     Acc",
        "------  ------  ------  ------  ------  --------  ------",
        "0.0000  0.0000  0.0000  0.0000  0.0000    0.0000  0.0000",
        "Used time: 0.1056 seconds"
      ]
    }
  ],
  "quality_valid": true
}